{
    "alps": [
        {
            "name": "grand_jorasses",
            "title": "Grand Jorasses",
            "img": "IMG_4408-thumb.jpg"
        },
        {
            "name": "climber_on_the_aiguilles_of_charmonix",
            "title": "Climber on the Aiguilles of Charmonix",
            "img": "IMG_4681-thumb.jpg"
        },
        {
            "name": "church_portico_zermat",
            "title": "Church Portico @ Zermat",
            "img": "IMG_4423-thumb.jpg"
        },
        {
            "name": "aiguilles_de_charmoz",
            "title": "Aiguilles de Charmoz",
            "img": "IMG_4425-thumb.jpg"
        },
        {
            "name": "ceiling_of_chapel_blatten",
            "title": "Ceiling of Chapel Blatten",
            "img": "IMG_4417-thumb.jpg"
        },
        {
            "name": "church_lotschental",
            "title": "Church @ Lotschental",
            "img": "IMG_4410-thumb.jpg"
        },
        {
            "name": "aiguilles_de_chamonix_cirque",
            "title": "Aiguilles de Chamonix Cirque",
            "img": "IMG_4420-thumb.jpg"
        },
        {
            "name": "toadstool_footing_on_barn",
            "title": "Toadstool Footing on Barn",
            "img": "IMG_4403-thumb.jpg"
        },
        {
            "name": "eiger_from_the_schilthorn",
            "title": "Eiger from the Schilthorn",
            "img": "IMG_4013-thumb.jpg"
        }
    ],
    "canada": [
        {
            "name": "neils_harbor",
            "title": "Neil's Harbor",
            "img": "Neils-Harbor-thumb.jpg"
        },
        {
            "name": "church_cape_breton",
            "title": "Church @ Cape Breton",
            "img": "IMG_4328-thumb.jpg"
        },
        {
            "name": "sand_river_alcove_stream",
            "title": "Sand River Alcove & Stream",
            "img": "IMG_4325-thumb.jpg"
        },
        {
            "name": "cemetery_in_mist",
            "title": "Cemetery in Mist",
            "img": "IMG_3963-thumb.jpg"
        },
        {
            "name": "bunch_berries",
            "title": "Bunch Berries",
            "img": "IMG_3962-thumb.jpg"
        },
        {
            "name": "window_thimble_berries",
            "title": "Window & Thimble Berries",
            "img": "IMG_3959-thumb.jpg"
        }
    ],
    "canadian_rockies": [
        {
            "name": "tree_and_fall",
            "title": "Tree and Fall",
            "img": "Tree-and-Fall-thumb.jpg"
        },
        {
            "name": "beauty_creek",
            "title": "Beauty Creek",
            "img": "Beauty-Creek-thumb.jpg"
        },
        {
            "name": "rock_and_rapids",
            "title": "Rock and Rapids",
            "img": "Rock-and-Rapids-thumb.jpg"
        },
        {
            "name": "pyramid_lake",
            "title": "Pyramid Lake",
            "img": "Pyramid-Lake-thumb.jpg"
        }
    ],
    "cathedral_portfolio": [
        {
            "name": "fountains_abby",
            "title": "Fountains Abby",
            "img": "IMG_4646-thumb.jpg"
        },
        {
            "name": "central_crossing_-_norwich",
            "title": "Central Crossing - Norwich",
            "img": "IMG_4641-thumb.jpg"
        },
        {
            "name": "lady_chapel_ceiling_-_wells",
            "title": "Lady Chapel Ceiling - Wells",
            "img": "IMG_4643-thumb.jpg"
        },
        {
            "name": "three_statues_-_wells",
            "title": "Three Statues - Wells",
            "img": "IMG_4639-thumb.jpg"
        },
        {
            "name": "angel_choir_column_-_lincoln",
            "title": "Angel Choir Column - Lincoln",
            "img": "IMG_4636-thumb.jpg"
        },
        {
            "name": "five_sisters_window_-_york",
            "title": "Five Sisters Window - York",
            "img": "IMG_4630-thumb.jpg"
        },
        {
            "name": "chapter_house_central_column_-_wells",
            "title": "Chapter House Central Column - Wells",
            "img": "IMG_4627-thumb.jpg"
        },
        {
            "name": "cloister_ceiling_-_gloucester",
            "title": "Cloister Ceiling - Gloucester",
            "img": "IMG_4619-thumb.jpg"
        },
        {
            "name": "crypt_with_figure_-_salisbury",
            "title": "Crypt with Figure - Salisbury",
            "img": "IMG_4618-thumb.jpg"
        },
        {
            "name": "lantern_screen_-_ely",
            "title": "Lantern Screen - Ely",
            "img": "IMG_4614-thumb.jpg"
        },
        {
            "name": "nave_-_exeter",
            "title": "Nave - Exeter",
            "img": "IMG_4610-thumb.jpg"
        }
    ],
    "flowers_on_black": [
        {
            "name": "cattleya",
            "title": "Cattleya",
            "img": "Cattleya-thumb.jpg"
        },
        {
            "name": "star-tulip",
            "title": "Star-Tulip",
            "img": "Star-Tulip-thumb.jpg"
        },
        {
            "name": "dancing_tulip",
            "title": "Dancing Tulip",
            "img": "Dancing-Tulip-thumb.jpg"
        },
        {
            "name": "pale_moth_orchid",
            "title": "Pale Moth Orchid",
            "img": "Pale-Moth-Orchid-thumb.jpg"
        },
        {
            "name": "moth_orchid",
            "title": "Moth Orchid",
            "img": "Moth-Orchid-thumb.jpg"
        },
        {
            "name": "narcisuss",
            "title": "Narcisuss",
            "img": "Narcisuss-thumb.jpg"
        },
        {
            "name": "apple_blossom_orchid",
            "title": "Apple Blossom Orchid",
            "img": "Apple-Blossom-Orchid-thumb.jpg"
        },
        {
            "name": "freebird",
            "title": "Freebird",
            "img": "Freebird-thumb.jpg"
        },
        {
            "name": "phalaenopsis",
            "title": "Phalaenopsis",
            "img": "Phalaenopsis-thumb.jpg"
        }
    ],
    "flowers_on_white": [
        {
            "name": "dahlia",
            "title": "Dahlia",
            "img": "IMG_4586-thumb.jpg"
        },
        {
            "name": "white_narcissus",
            "title": "White Narcissus",
            "img": "IMG_4585-thumb.jpg"
        },
        {
            "name": "clemantis",
            "title": "Clemantis",
            "img": "IMG_4582-thumb.jpg"
        },
        {
            "name": "black-eyed_susan",
            "title": "Black-eyed Susan",
            "img": "IMG_4579-thumb.jpg"
        },
        {
            "name": "himalayan_irises",
            "title": "Himalayan Irises",
            "img": "IMG_4573-thumb.jpg"
        },
        {
            "name": "spider_amaryllis",
            "title": "Spider Amaryllis",
            "img": "IMG_4576-thumb.jpg"
        },
        {
            "name": "glads",
            "title": "Glads",
            "img": "IMG_4567-thumb.jpg"
        },
        {
            "name": "dogwood",
            "title": "Dogwood",
            "img": "IMG_4564-thumb.jpg"
        },
        {
            "name": "white_iris",
            "title": "White Iris",
            "img": "IMG_4561-thumb.jpg"
        },
        {
            "name": "tulips",
            "title": "Tulips",
            "img": "IMG_4558-thumb.jpg"
        },
        {
            "name": "peony",
            "title": "Peony",
            "img": "IMG_4555-thumb.jpg"
        },
        {
            "name": "gerbera_daisy",
            "title": "Gerbera Daisy",
            "img": "IMG_4552-thumb.jpg"
        },
        {
            "name": "two_iris",
            "title": "Two Iris",
            "img": "IMG_4549-thumb.jpg"
        },
        {
            "name": "mums",
            "title": "Mums",
            "img": "IMG_4544-thumb.jpg"
        },
        {
            "name": "magnolia",
            "title": "Magnolia",
            "img": "IMG_4543-thumb.jpg"
        },
        {
            "name": "canadian_thistle",
            "title": "Canadian Thistle",
            "img": "DCP_0721-thumb.jpg"
        }
    ],
    "grand_canyon": [
        {
            "name": "bright_angel_trail",
            "title": "Bright Angel Trail",
            "img": "IMG_4534-thumb.jpg"
        },
        {
            "name": "storm_over_grand_canyon",
            "title": "Storm over Grand Canyon",
            "img": "IMG_4529-thumb.jpg"
        },
        {
            "name": "shrub_mathers_point",
            "title": "Shrub @ Mather's Point",
            "img": "IMG_4538-thumb.jpg"
        },
        {
            "name": "rock_mathers_point",
            "title": "Rock @ Mather's Point",
            "img": "IMG_4526-thumb.jpg"
        }
    ],
    "great_britain": [
        {
            "name": "durham_-_nave_with_round_window",
            "title": "Durham - Nave with Round Window",
            "img": "IMG_4297-thumb.jpg"
        },
        {
            "name": "oxford_-_divinity_school",
            "title": "Oxford - Divinity School",
            "img": "IMG_4295-thumb.jpg"
        },
        {
            "name": "wells_-_chapter_house_central_column",
            "title": "Wells - Chapter House Central Column",
            "img": "IMG_4289-thumb.jpg"
        },
        {
            "name": "ely_-_lantern",
            "title": "Ely - Lantern",
            "img": "IMG_4290-thumb.jpg"
        },
        {
            "name": "peterborough_-_central_crossing",
            "title": "Peterborough - Central Crossing",
            "img": "IMG_4275-thumb.jpg"
        },
        {
            "name": "lincoln_-_central_crossing",
            "title": "Lincoln - Central Crossing",
            "img": "IMG_4274-thumb.jpg"
        },
        {
            "name": "durham_-_central_crossing",
            "title": "Durham - Central Crossing",
            "img": "IMG_4271-thumb.jpg"
        },
        {
            "name": "wells_-_nave",
            "title": "Wells - Nave",
            "img": "IMG_4265-thumb.jpg"
        },
        {
            "name": "norwich_-_cloister",
            "title": "Norwich - Cloister",
            "img": "IMG_4262-thumb.jpg"
        },
        {
            "name": "wells_-_organ",
            "title": "Wells - Organ",
            "img": "IMG_4604-thumb.jpg"
        },
        {
            "name": "wells_-_retrochoir_and_lady_chapel",
            "title": "Wells - Retrochoir and Lady Chapel",
            "img": "IMG_4603-thumb.jpg"
        },
        {
            "name": "lincoln_-_cloister_ceiling",
            "title": "Lincoln - Cloister Ceiling",
            "img": "IMG_4311-thumb.jpg"
        },
        {
            "name": "lincoln_-_chapter_house",
            "title": "Lincoln - Chapter House",
            "img": "IMG_4308-thumb.jpg"
        },
        {
            "name": "ely_-_choir",
            "title": "Ely - Choir",
            "img": "IMG_4305-thumb.jpg"
        },
        {
            "name": "lincoln_-_nave",
            "title": "Lincoln - Nave",
            "img": "IMG_4303-thumb.jpg"
        },
        {
            "name": "norwich_-_choir_from_central_crossing",
            "title": "Norwich - Choir from Central Crossing",
            "img": "IMG_4301-thumb.jpg"
        },
        {
            "name": "norwich_-_nave",
            "title": "Norwich - Nave",
            "img": "IMG_4259-thumb.jpg"
        },
        {
            "name": "exeter_-_choir_ceiling",
            "title": "Exeter - Choir Ceiling",
            "img": "IMG_4253-thumb.jpg"
        },
        {
            "name": "exeter_-_choir_ceiling_detail",
            "title": "Exeter - Choir Ceiling Detail",
            "img": "IMG_4250-thumb.jpg"
        },
        {
            "name": "door_stow-on-the-wold",
            "title": "Door @ Stow-on-the-Wold",
            "img": "IMG_4663-thumb.jpg"
        },
        {
            "name": "hanging_ivy",
            "title": "Hanging Ivy",
            "img": "IMG_4286-thumb.jpg"
        },
        {
            "name": "kilchurn_castle_-_scotland",
            "title": "Kilchurn Castle - Scotland",
            "img": "IMG_4281-thumb.jpg"
        },
        {
            "name": "loch_lomond",
            "title": "Loch Lomond",
            "img": "IMG_4278-thumb.jpg"
        }
    ],
    "great_sand_dunes": [
        {
            "name": "dune_dunettes",
            "title": "Dune & Dunettes",
            "img": "IMG_4485-thumb.jpg"
        },
        {
            "name": "gentle_dunes",
            "title": "Gentle Dunes",
            "img": "IMG_4483-thumb.jpg"
        },
        {
            "name": "medano_creek",
            "title": "Medano Creek",
            "img": "IMG_4478-thumb.jpg"
        },
        {
            "name": "dead_tree",
            "title": "Dead Tree",
            "img": "IMG_4475-thumb.jpg"
        },
        {
            "name": "dune_sky",
            "title": "Dune Sky",
            "img": "IMG_4471-thumb.jpg"
        },
        {
            "name": "big_pine",
            "title": "Big Pine",
            "img": "IMG_4467-thumb.jpg"
        }
    ],
    "greek_islands": [
        {
            "name": "window_at_pyrogos",
            "title": "Window at Pyrogos",
            "img": "Windw-at-Pyrogos-thumb.jpg"
        },
        {
            "name": "sleeping_dog-ios",
            "title": "Sleeping Dog-Ios",
            "img": "Sleeping-Dog-Ios-thumb.jpg"
        },
        {
            "name": "bricked_up_door",
            "title": "Bricked up Door",
            "img": "Bricked-up-Door-thumb.jpg"
        },
        {
            "name": "church_with_round_hole_at_oia",
            "title": "Church with Round Hole at Oia",
            "img": "Church-with-Round-Hole-at-Oia-thumb.jpg"
        },
        {
            "name": "ruin_ceiling_at_oia",
            "title": "Ruin Ceiling at Oia",
            "img": "Ruin-Ceiling-at-Oia-thumb.jpg"
        },
        {
            "name": "arch_design_at_church_of_100_doors",
            "title": "Arch Design at Church of 100 Doors",
            "img": "Arch-Design-at-Church-of-100-thumb.jpg"
        },
        {
            "name": "atlantis_entrance_paros",
            "title": "Atlantis Entrance Paros",
            "img": "Atlantis-Entrance-Paros-thumb.jpg"
        },
        {
            "name": "ceiling_of_church_emporio",
            "title": "Ceiling of Church Emporio",
            "img": "Ceiling-of-Church-Emporio-thumb.jpg"
        },
        {
            "name": "church_arches_ios",
            "title": "Church Arches Ios",
            "img": "Church-Arches-Ios-thumb.jpg"
        },
        {
            "name": "church_small_window",
            "title": "Church Small Window",
            "img": "Church-Small-Window-thumb.jpg"
        },
        {
            "name": "design_pyrogos",
            "title": "Design Pyrogos",
            "img": "Design-Pyrogos-thumb.jpg"
        },
        {
            "name": "door_with_white_cross",
            "title": "Door with White Cross",
            "img": "Door-with-White-Cross-thumb.jpg"
        },
        {
            "name": "hill_church_on_ios",
            "title": "Hill Church on Ios",
            "img": "Hill-church-on-Ios-thumb.jpg"
        },
        {
            "name": "homerick_poems_thira",
            "title": "Homerick Poems Thira",
            "img": "Homerick-Poems-Thira-thumb.jpg"
        },
        {
            "name": "passage_way_pyrogos",
            "title": "Passage Way Pyrogos",
            "img": "Passage-Way-Pyrogos-thumb.jpg"
        },
        {
            "name": "window_lefkes",
            "title": "Window Lefkes",
            "img": "Window-Lefkes-thumb.jpg"
        },
        {
            "name": "window_lenicel",
            "title": "Window Lenicel",
            "img": "Window-Lenicel-thumb.jpg"
        },
        {
            "name": "woman_at_window",
            "title": "Woman at Window",
            "img": "Woman-at-Window-thumb.jpg"
        }
    ],
    "ireland": [
        {
            "name": "gilroys_pub",
            "title": "Gilroy's Pub",
            "img": "Gilroys-Pub-thumb.jpg"
        },
        {
            "name": "imbibing_on_castle_st",
            "title": "Imbibing on Castle St.",
            "img": "Imbibing-on-Castle-St.-thumb.jpg"
        },
        {
            "name": "door_75",
            "title": "Door #75",
            "img": "IMG_4686-thumb.jpg"
        },
        {
            "name": "door_60",
            "title": "Door #60",
            "img": "IMG_4684-thumb.jpg"
        },
        {
            "name": "glendalough_gravestones",
            "title": "Glendalough Gravestones",
            "img": "IMG_4452-thumb.jpg"
        },
        {
            "name": "farmhouse_dingle",
            "title": "Farmhouse @ Dingle",
            "img": "IMG_4448-thumb.jpg"
        },
        {
            "name": "dunluce_castle",
            "title": "Dunluce Castle",
            "img": "IMG_4446-thumb.jpg"
        }
    ],
    "michigan_ohio": [
        {
            "name": "laurel_creek",
            "title": "Laurel Creek",
            "img": "Laurel-Creek-thumb.jpg"
        },
        {
            "name": "two_pigeons",
            "title": "Two Pigeons",
            "img": "Two-Pigeons-thumb.jpg"
        },
        {
            "name": "laughing_whitefish_falls",
            "title": "Laughing Whitefish Falls",
            "img": "Laughing-Whitefish Falls-thumb.jpg"
        },
        {
            "name": "devils_bathtub",
            "title": "Devil's Bathtub",
            "img": "IMG_4709-thumb.jpg"
        },
        {
            "name": "window_law_quad",
            "title": "Window @ Law Quad",
            "img": "IMG_4691-thumb.jpg"
        },
        {
            "name": "encircled_tree",
            "title": "Encircled Tree",
            "img": "IMG_4499-thumb.jpg"
        },
        {
            "name": "tannin_falls",
            "title": "Tannin Falls",
            "img": "IMG_4497-thumb.jpg"
        },
        {
            "name": "scott_falls",
            "title": "Scott Falls",
            "img": "IMG_4491-thumb.jpg"
        }
    ],
    "mystic_tulip": [],
    "netherlands": [
        {
            "name": "bedding",
            "title": "Bedding",
            "img": "Bedding-thumb.jpg"
        },
        {
            "name": "corner_store",
            "title": "Corner Store",
            "img": "Corner-Store-thumb.jpg"
        },
        {
            "name": "five_bridges",
            "title": "Five Bridges",
            "img": "IMG_4703-thumb.jpg"
        },
        {
            "name": "tile_roof",
            "title": "Tile Roof",
            "img": "IMG_4700-thumb.jpg"
        },
        {
            "name": "dutch_canal",
            "title": "Dutch Canal",
            "img": "IMG_4697-thumb.jpg"
        },
        {
            "name": "window_buren",
            "title": "Window @ Buren",
            "img": "IMG_4694-thumb.jpg"
        },
        {
            "name": "church_thorn",
            "title": "Church @ Thorn",
            "img": "IMG_4657-thumb.jpg"
        }
    ],
    "southwest": [
        {
            "name": "wave_1",
            "title": "Wave #1",
            "img": "Wave1-thumb.jpg"
        },
        {
            "name": "wave_2_detail",
            "title": "Wave #2 Detail",
            "img": "Wave2-Detail-thumb.jpg"
        },
        {
            "name": "wave_2",
            "title": "Wave #2",
            "img": "Wave2-thumb.jpg"
        },
        {
            "name": "wave_1_detail",
            "title": "Wave #1 Detail",
            "img": "Wave1-Detail-thumb.jpg"
        },
        {
            "name": "wave",
            "title": "Wave",
            "img": "Wave-thumb.jpg"
        },
        {
            "name": "wave_entrance",
            "title": "Wave Entrance",
            "img": "Wave-Entrance-thumb.jpg"
        },
        {
            "name": "three_faces",
            "title": "Three Faces",
            "img": "Three-Faces-thumb.jpg"
        },
        {
            "name": "sweep",
            "title": "Sweep",
            "img": "Sweep-thumb.jpg"
        },
        {
            "name": "skeleton_tree",
            "title": "Skeleton Tree",
            "img": "Skeleton-Tree-thumb.jpg"
        },
        {
            "name": "side_entrance_to_wave",
            "title": "Side Entrance to Wave",
            "img": "Side-Entrance-to-Wave-thumb.jpg"
        },
        {
            "name": "rock_formations",
            "title": "Rock Formations",
            "img": "Rock-Formations-thumb.jpg"
        },
        {
            "name": "hoodoos",
            "title": "Hoodoos",
            "img": "Hoodoos-thumb.jpg"
        },
        {
            "name": "ghosts",
            "title": "Ghosts",
            "img": "Ghosts-thumb.jpg"
        },
        {
            "name": "candy_canyon",
            "title": "Candy Canyon",
            "img": "Candy-Canyon-thumb.jpg"
        },
        {
            "name": "white_bush",
            "title": "White Bush",
            "img": "IMG_4454-thumb.jpg"
        },
        {
            "name": "ice_cave",
            "title": "Ice Cave",
            "img": "IMG_4441-thumb.jpg"
        },
        {
            "name": "white_wave",
            "title": "White Wave",
            "img": "IMG_4436-thumb.jpg"
        },
        {
            "name": "lower_mule_canyon",
            "title": "Lower Mule Canyon",
            "img": "IMG_4399-thumb.jpg"
        },
        {
            "name": "sunlit_cave",
            "title": "Sunlit Cave",
            "img": "IMG_4395-thumb.jpg"
        },
        {
            "name": "road_canyon_ruins",
            "title": "Road Canyon Ruins",
            "img": "IMG_4393-thumb.jpg"
        },
        {
            "name": "sponge_rock",
            "title": "Sponge Rock",
            "img": "IMG_4388-thumb.jpg"
        },
        {
            "name": "rt_95_tree_two_rocks",
            "title": "Rt 95 Tree & Two Rocks",
            "img": "IMG_4387-thumb.jpg"
        },
        {
            "name": "green_river_overlook",
            "title": "Green River Overlook",
            "img": "IMG_4383-thumb.jpg"
        },
        {
            "name": "monarch_cave_city",
            "title": "Monarch Cave City",
            "img": "IMG_4380-thumb.jpg"
        },
        {
            "name": "upper_mule_canyon_ruins",
            "title": "Upper Mule Canyon Ruins",
            "img": "IMG_4378-thumb.jpg"
        },
        {
            "name": "monarch_cave_house",
            "title": "Monarch Cave House",
            "img": "IMG_4373-thumb.jpg"
        },
        {
            "name": "hog_spring",
            "title": "Hog Spring",
            "img": "IMG_4372-thumb.jpg"
        },
        {
            "name": "little_wild_horse",
            "title": "Little Wild Horse",
            "img": "IMG_4014-thumb.jpg"
        }
    ],
    "tetons": [
        {
            "name": "hidden_fall",
            "title": "Hidden Fall",
            "img": "IMG_4523-thumb.jpg"
        },
        {
            "name": "tetons_-_reflection_horiz",
            "title": "Tetons - Reflection (Horiz.)",
            "img": "IMG_4520-thumb.jpg"
        },
        {
            "name": "tetons_-_reflection_vert",
            "title": "Tetons - Reflection (Vert.)",
            "img": "IMG_4517-thumb.jpg"
        },
        {
            "name": "tetons_snake_river",
            "title": "Tetons & Snake River",
            "img": "IMG_4515-thumb.jpg"
        },
        {
            "name": "sunrise_-_mt_moran",
            "title": "Sunrise - Mt. Moran",
            "img": "IMG_4512-thumb.jpg"
        },
        {
            "name": "river_of_light",
            "title": "River of Light",
            "img": "IMG_4508-thumb.jpg"
        },
        {
            "name": "string_lake",
            "title": "String Lake",
            "img": "IMG_4502-thumb.jpg"
        }
    ],
    "united_states_rockies": [
        {
            "name": "white_tree_adams_falls",
            "title": "White Tree Adams Falls",
            "img": "White-Tree-Adams-Falls-thumb.jpg"
        },
        {
            "name": "lake_grandby_in_fog",
            "title": "Lake Grandby in Fog",
            "img": "Lake-Grandby-in-Fog-thumb.jpg"
        },
        {
            "name": "fall_aspens",
            "title": "Fall Aspens",
            "img": "Fall-Aspens-thumb.jpg"
        },
        {
            "name": "colorado_headwater_in_fog",
            "title": "Colorado Headwater in Fog",
            "img": "Colorado-Headwater-in-Fog-thumb.jpg"
        },
        {
            "name": "aspen_backlite",
            "title": "Aspen Backlite",
            "img": "Aspen-Backlite-thumb.jpg"
        }
    ],
    "yosemite": [
        {
            "name": "upper_yosemite_falls",
            "title": "Upper Yosemite Falls",
            "img": "IMG_4706-thumb.jpg"
        },
        {
            "name": "sunrise_on_the_merced",
            "title": "Sunrise on the Merced",
            "img": "IMG_4677-thumb.jpg"
        },
        {
            "name": "shadow_fall",
            "title": "Shadow Fall",
            "img": "IMG_4674-thumb.jpg"
        },
        {
            "name": "half_dome",
            "title": "Half Dome",
            "img": "IMG_4673-thumb.jpg"
        },
        {
            "name": "ansel_adams",
            "title": "Ansel Adams",
            "img": "IMG_4607-thumb.jpg"
        },
        {
            "name": "mirror_lake",
            "title": "Mirror Lake",
            "img": "IMG_4595-thumb.jpg"
        }
    ],
    "zion": [
        {
            "name": "two_trees_in_creek",
            "title": "Two Trees in Creek",
            "img": "Two-Trees-in-Creek-thumb.jpg"
        },
        {
            "name": "curved_wall_with_tree",
            "title": "Curved Wall with Tree",
            "img": "Curved-Wall-with-Tree-thumb.jpg"
        },
        {
            "name": "north_canyon_entrance",
            "title": "North Canyon Entrance",
            "img": "North-Canyon-Entrance-thumb.jpg"
        },
        {
            "name": "hidden_valley",
            "title": "Hidden Valley",
            "img": "IMG_4715-thumb.jpg"
        },
        {
            "name": "distance_view_through_trees",
            "title": "Distance View through Trees",
            "img": "IMG_4712-thumb.jpg"
        },
        {
            "name": "hidden_valley_wall",
            "title": "Hidden Valley Wall",
            "img": "IMG_4363-thumb.jpg"
        },
        {
            "name": "lower_emerald_falls",
            "title": "Lower Emerald Falls",
            "img": "IMG_4358-thumb.jpg"
        },
        {
            "name": "fall_white_tree_on_the_virgin_river",
            "title": "Fall White Tree on the Virgin River",
            "img": "IMG_4357-thumb.jpg"
        },
        {
            "name": "spring_white_tree_on_the_virgin_river",
            "title": "Spring White Tree on the Virgin River",
            "img": "IMG_4354-thumb.jpg"
        }
    ]
}